trainable/__init__.py
trainable/algorithm.py
trainable/epoch.py
trainable/progress.py
trainable/session.py
trainable/test.py
trainable/trainer.py
trainable/validate.py
trainable/visualize.py
trainable/data/__init__.py
trainable/data/datasets.py
trainable/data/transforms.py
trainable/features/__init__.py
trainable/features/features.py
trainable/features/vgg.py
trainable/models/__init__.py
trainable/models/autoencoder.py
trainable-0.1.3.post9.dist-info/METADATA
trainable-0.1.3.post9.dist-info/RECORD
trainable-0.1.3.post9.dist-info/WHEEL
trainable-0.1.3.post9.dist-info/top_level.txt
